pytest_sosu/__init__.py
pytest_sosu/_version.py
pytest_sosu/config.py
pytest_sosu/exceptions.py
pytest_sosu/logging.py
pytest_sosu/plugin.py
pytest_sosu/plugin_helpers.py
pytest_sosu/typing.py
pytest_sosu/utils.py
pytest_sosu/webdriver/__init__.py
pytest_sosu/webdriver/capabilities.py
pytest_sosu/webdriver/compat.py
pytest_sosu/webdriver/platforms.py
pytest_sosu/webdriver/selenium.py
pytest_sosu/webdriver/url.py
pytest_sosu-0.3.1.dist-info/LICENSE
pytest_sosu-0.3.1.dist-info/METADATA
pytest_sosu-0.3.1.dist-info/WHEEL
pytest_sosu-0.3.1.dist-info/entry_points.txt
pytest_sosu-0.3.1.dist-info/top_level.txt
pytest_sosu-0.3.1.dist-info/RECORD
