Metadata-Version: 2.1
Name: pytest-sosu
Version: 0.3.1
Summary: Unofficial PyTest plugin for Sauce Labs
Author-email: Andrzej Pragacz <apragacz@o2.pl>
License: MIT License
Project-URL: homepage, https://github.com/apragacz/pytest-sosu
Project-URL: Bug Tracker, https://github.com/apragacz/pytest-sosu/issues
Project-URL: Documentation, https://github.com/apragacz/pytest-sosu/blob/master/README.md
Project-URL: Source Code, https://github.com/apragacz/pytest-sosu
Keywords: pytest,selenium,webdriver,saucelabs,sauce,sosu
Classifier: Development Status :: 2 - Pre-Alpha
Classifier: Framework :: Pytest
Classifier: Intended Audience :: Customer Service
Classifier: Intended Audience :: Developers
Classifier: License :: OSI Approved :: MIT License
Classifier: Operating System :: POSIX
Classifier: Operating System :: POSIX :: Linux
Classifier: Programming Language :: Python
Classifier: Programming Language :: Python :: 3
Classifier: Programming Language :: Python :: 3 :: Only
Classifier: Topic :: Software Development :: Testing
Requires-Python: >=3.7
License-File: LICENSE
Requires-Dist: pytest
Requires-Dist: selenium (>=4.11)
